cjajb_athletics/__init__.py
cjajb_athletics/run.py
cjajb_athletics/technic.py
cjajb_athletics-1.0.0.dist-info/METADATA
cjajb_athletics-1.0.0.dist-info/WHEEL
cjajb_athletics-1.0.0.dist-info/licenses/LICENSE
cjajb_athletics-1.0.0.dist-info/RECORD
