Metadata-Version: 2.3
Name: cjajb_athletics
Version: 1.0.0
Summary: A package to compute all the athletics scores of the CJAJB Meetings
Project-URL: Hompage, https://github.com/Rodama-20/Athletics
Project-URL: Bug Tracker, https://github.com/Rodama-20/Athletics/issues
Author-email: Cyrille Polier <rodama20@gmail.com>
License-File: LICENSE
Classifier: License :: OSI Approved :: MIT License
Classifier: Operating System :: OS Independent
Classifier: Programming Language :: Python :: 3
Requires-Python: >=3.10
Requires-Dist: numpy
